vpselector/__init__.py
vpselector/data_selection.py
vpselector/widgets/__init__.py
vpselector/widgets/dataframe_plot_widget.py
vpselector/widgets/histogram_plot_widget.py
vpselector/widgets/mpl_widget.py
vpselector/widgets/time_series_data_plot_widget.py
vpselector/windows/__init__.py
vpselector/windows/confirm_selection_window.py
vpselector/windows/main_window.py
vpselector-1.0.2.dist-info/LICENSE.txt
vpselector-1.0.2.dist-info/WHEEL
vpselector-1.0.2.dist-info/METADATA
vpselector-1.0.2.dist-info/RECORD
