Metadata-Version: 2.1
Name: vpselector
Version: 1.0.2
Summary: Visualize and interactively select time-series data from a pandas DataFrame.
Keywords: python,dataframe,pandas,visualization,data selection,time-series data,data tools,data science,data-driven engineering,machine learning,system identification
Author: Manuel Yves Galliker
Author-email: manuel@galliker.tech
Maintainer-email: Manuel Yves Galliker <manuel@galliker.tech>
Requires-Python: >=3.8
Classifier: Development Status :: 4 - Beta
Classifier: Programming Language :: Python
Requires-Dist: pandas >= 1.1.5
Requires-Dist: PyQt5>=5.15.0
Requires-Dist: matplotlib>=3.7.1
Requires-Dist: seaborn>=0.11.1
Requires-Dist: overrides>=7.3.1
Requires-Dist: twine>=4.0.2
Requires-Dist: black >= 23.3.0 ; extra == "format"
Project-URL: repository, https://github.com/manumerous/vpselector
Provides-Extra: format
